[
  { "startup": "Stripe", "industry": "Fintech", "amount": 150000000, "year": 2016 },
  { "startup": "Slack", "industry": "Communication", "amount": 160000000, "year": 2017 },
  { "startup": "Robinhood", "industry": "Fintech", "amount": 110000000, "year": 2018 },
  { "startup": "Notion", "industry": "Productivity", "amount": 100000000, "year": 2020 },
  { "startup": "Airtable", "industry": "Productivity", "amount": 185000000, "year": 2021 },
  { "startup": "Figma", "industry": "Design", "amount": 200000000, "year": 2020 },
  { "startup": "Gong", "industry": "AI", "amount": 70000000, "year": 2019 },
  { "startup": "Coda", "industry": "Productivity", "amount": 80000000, "year": 2021 },
  { "startup": "Brex", "industry": "Fintech", "amount": 150000000, "year": 2021 },
  { "startup": "Miro", "industry": "Collaboration", "amount": 176000000, "year": 2021 },
  { "startup": "Plaid", "industry": "Fintech", "amount": 425000000, "year": 2021 },
  { "startup": "Databricks", "industry": "Data", "amount": 400000000, "year": 2021 },
  { "startup": "UiPath", "industry": "Automation", "amount": 75000000, "year": 2019 },
  { "startup": "Toast", "industry": "Restaurant Tech", "amount": 40000000, "year": 2018 },
  { "startup": "Chime", "industry": "Fintech", "amount": 70000000, "year": 2019 },
  { "startup": "DoorDash", "industry": "Food Delivery", "amount": 60000000, "year": 2018 },
  { "startup": "Coinbase", "industry": "Cryptocurrency", "amount": 300000000, "year": 2018 },
  { "startup": "Lyft", "industry": "Transportation", "amount": 60000000, "year": 2017 },
  { "startup": "Airbnb", "industry": "Travel", "amount": 55000000, "year": 2017 },
  { "startup": "Pinterest", "industry": "Social Media", "amount": 50000000, "year": 2017 },
  { "startup": "Snapchat", "industry": "Social Media", "amount": 50000000, "year": 2017 },
  { "startup": "Uber", "industry": "Transportation", "amount": 50000000, "year": 2017 },
  { "startup": "WeWork", "industry": "Real Estate", "amount": 50000000, "year": 2017 },
  { "startup": "Zocdoc", "industry": "Health Tech", "amount": 50000000, "year": 2017 },
  { "startup": "Instacart", "industry": "Grocery Delivery", "amount": 50000000, "year": 2017 },
  { "startup": "Wish", "industry": "E-commerce", "amount": 50000000, "year": 2017 },
  { "startup": "Postmates", "industry": "Food Delivery", "amount": 50000000, "year": 2017 },
  { "startup": "Robinhood", "industry": "Fintech", "amount": 50000000, "year": 2017 },
  { "startup": "Stripe", "industry": "Fintech", "amount": 50000000, "year": 2017 },
  { "startup": "Slack", "industry": "Communication", "amount": 50000000, "year": 2017 },
  { "startup": "Zoom", "industry": "Communication", "amount": 50000000, "year": 2017 },
  { "startup": "Lyft", "industry": "Transportation", "amount": 50000000, "year": 2017 },
  { "startup": "DoorDash", "industry": "Food Delivery", "amount": 50000000, "year": 2017 }
]
